<?xml version="1.0" encoding="UTF-8"?>
<ARRAY type="de.espirit.firstspirit.access.store.templatestore.TableTemplate$Mapping">
	<OBJECT class="de.espirit.firstspirit.access.store.templatestore.FieldMapping">
		<FIELD name="_dbAttributeNames">
			<OBJECT class="java.util.HashMap">
				<OBJECT class="java.lang.String">DE</OBJECT>
				<ARRAY type="java.lang.String">
					<OBJECT class="java.lang.String">type</OBJECT>
				</ARRAY>
				<OBJECT class="java.lang.String">EN</OBJECT>
				<ARRAY type="java.lang.String">
					<OBJECT class="java.lang.String">type</OBJECT>
				</ARRAY>
			</OBJECT>
		</FIELD>
		<FIELD name="_dbReferenceName"><NULL/><!-- class java.lang.String --></FIELD>
		<FIELD name="_displayNames">
			<OBJECT class="java.util.HashMap">
				<OBJECT class="java.lang.String">DE</OBJECT>
				<OBJECT class="java.lang.String">Standorttype</OBJECT>
				<OBJECT class="java.lang.String">EN</OBJECT>
				<OBJECT class="java.lang.String">Locationtype</OBJECT>
			</OBJECT>
		</FIELD>
		<FIELD name="_name">
			<OBJECT class="java.lang.String">tt_location_type</OBJECT>
		</FIELD>
		<FIELD name="_valueListAttribute"><NULL/><!-- class [Ljava.lang.String; --></FIELD>
		<FIELD name="_visible" type="boolean">true</FIELD>
		<FIELD name="_width" type="int">120</FIELD>
	</OBJECT>
	<OBJECT class="de.espirit.firstspirit.access.store.templatestore.FieldMapping">
		<FIELD name="_dbAttributeNames">
			<OBJECT class="java.util.HashMap">
				<OBJECT class="java.lang.String">DE</OBJECT>
				<ARRAY type="java.lang.String">
					<OBJECT class="java.lang.String">firma</OBJECT>
				</ARRAY>
				<OBJECT class="java.lang.String">EN</OBJECT>
				<ARRAY type="java.lang.String">
					<OBJECT class="java.lang.String">firma</OBJECT>
				</ARRAY>
			</OBJECT>
		</FIELD>
		<FIELD name="_dbReferenceName"><NULL/><!-- class java.lang.String --></FIELD>
		<FIELD name="_displayNames">
			<OBJECT class="java.util.HashMap">
				<OBJECT class="java.lang.String">DE</OBJECT>
				<OBJECT class="java.lang.String">Firma</OBJECT>
				<OBJECT class="java.lang.String">EN</OBJECT>
				<OBJECT class="java.lang.String">Company</OBJECT>
			</OBJECT>
		</FIELD>
		<FIELD name="_name">
			<OBJECT class="java.lang.String">tt_company</OBJECT>
		</FIELD>
		<FIELD name="_valueListAttribute"><NULL/><!-- class [Ljava.lang.String; --></FIELD>
		<FIELD name="_visible" type="boolean">true</FIELD>
		<FIELD name="_width" type="int">120</FIELD>
	</OBJECT>
	<OBJECT class="de.espirit.firstspirit.access.store.templatestore.FieldMapping">
		<FIELD name="_dbAttributeNames">
			<OBJECT class="java.util.HashMap">
				<OBJECT class="java.lang.String">DE</OBJECT>
				<ARRAY type="java.lang.String">
					<OBJECT class="java.lang.String">description_DE</OBJECT>
				</ARRAY>
				<OBJECT class="java.lang.String">EN</OBJECT>
				<ARRAY type="java.lang.String">
					<OBJECT class="java.lang.String">description_EN</OBJECT>
				</ARRAY>
			</OBJECT>
		</FIELD>
		<FIELD name="_dbReferenceName"><NULL/><!-- class java.lang.String --></FIELD>
		<FIELD name="_displayNames">
			<OBJECT class="java.util.HashMap">
				<OBJECT class="java.lang.String">DE</OBJECT>
				<OBJECT class="java.lang.String">Ergänzende Beschreibung</OBJECT>
				<OBJECT class="java.lang.String">EN</OBJECT>
				<OBJECT class="java.lang.String">Description</OBJECT>
			</OBJECT>
		</FIELD>
		<FIELD name="_name">
			<OBJECT class="java.lang.String">tt_description</OBJECT>
		</FIELD>
		<FIELD name="_valueListAttribute"><NULL/><!-- class [Ljava.lang.String; --></FIELD>
		<FIELD name="_visible" type="boolean">true</FIELD>
		<FIELD name="_width" type="int">120</FIELD>
	</OBJECT>
	<OBJECT class="de.espirit.firstspirit.access.store.templatestore.FieldMapping">
		<FIELD name="_dbAttributeNames">
			<OBJECT class="java.util.HashMap">
				<OBJECT class="java.lang.String">DE</OBJECT>
				<ARRAY type="java.lang.String">
					<OBJECT class="java.lang.String">street</OBJECT>
				</ARRAY>
				<OBJECT class="java.lang.String">EN</OBJECT>
				<ARRAY type="java.lang.String">
					<OBJECT class="java.lang.String">street</OBJECT>
				</ARRAY>
			</OBJECT>
		</FIELD>
		<FIELD name="_dbReferenceName"><NULL/><!-- class java.lang.String --></FIELD>
		<FIELD name="_displayNames">
			<OBJECT class="java.util.HashMap">
				<OBJECT class="java.lang.String">DE</OBJECT>
				<OBJECT class="java.lang.String">Street</OBJECT>
				<OBJECT class="java.lang.String">EN</OBJECT>
				<OBJECT class="java.lang.String">Straße</OBJECT>
			</OBJECT>
		</FIELD>
		<FIELD name="_name">
			<OBJECT class="java.lang.String">tt_street</OBJECT>
		</FIELD>
		<FIELD name="_valueListAttribute"><NULL/><!-- class [Ljava.lang.String; --></FIELD>
		<FIELD name="_visible" type="boolean">true</FIELD>
		<FIELD name="_width" type="int">120</FIELD>
	</OBJECT>
	<OBJECT class="de.espirit.firstspirit.access.store.templatestore.FieldMapping">
		<FIELD name="_dbAttributeNames">
			<OBJECT class="java.util.HashMap">
				<OBJECT class="java.lang.String">DE</OBJECT>
				<ARRAY type="java.lang.String">
					<OBJECT class="java.lang.String">city</OBJECT>
				</ARRAY>
				<OBJECT class="java.lang.String">EN</OBJECT>
				<ARRAY type="java.lang.String">
					<OBJECT class="java.lang.String">city</OBJECT>
				</ARRAY>
			</OBJECT>
		</FIELD>
		<FIELD name="_dbReferenceName"><NULL/><!-- class java.lang.String --></FIELD>
		<FIELD name="_displayNames">
			<OBJECT class="java.util.HashMap">
				<OBJECT class="java.lang.String">DE</OBJECT>
				<OBJECT class="java.lang.String">Stadt</OBJECT>
				<OBJECT class="java.lang.String">EN</OBJECT>
				<OBJECT class="java.lang.String">City</OBJECT>
			</OBJECT>
		</FIELD>
		<FIELD name="_name">
			<OBJECT class="java.lang.String">tt_city</OBJECT>
		</FIELD>
		<FIELD name="_valueListAttribute"><NULL/><!-- class [Ljava.lang.String; --></FIELD>
		<FIELD name="_visible" type="boolean">true</FIELD>
		<FIELD name="_width" type="int">120</FIELD>
	</OBJECT>
	<OBJECT class="de.espirit.firstspirit.access.store.templatestore.FieldMapping">
		<FIELD name="_dbAttributeNames">
			<OBJECT class="java.util.HashMap">
				<OBJECT class="java.lang.String">DE</OBJECT>
				<ARRAY type="java.lang.String">
					<OBJECT class="java.lang.String">plz</OBJECT>
				</ARRAY>
				<OBJECT class="java.lang.String">EN</OBJECT>
				<ARRAY type="java.lang.String">
					<OBJECT class="java.lang.String">plz</OBJECT>
				</ARRAY>
			</OBJECT>
		</FIELD>
		<FIELD name="_dbReferenceName"><NULL/><!-- class java.lang.String --></FIELD>
		<FIELD name="_displayNames">
			<OBJECT class="java.util.HashMap">
				<OBJECT class="java.lang.String">DE</OBJECT>
				<OBJECT class="java.lang.String">PLZ</OBJECT>
				<OBJECT class="java.lang.String">EN</OBJECT>
				<OBJECT class="java.lang.String">PLZ</OBJECT>
			</OBJECT>
		</FIELD>
		<FIELD name="_name">
			<OBJECT class="java.lang.String">tt_plz</OBJECT>
		</FIELD>
		<FIELD name="_valueListAttribute"><NULL/><!-- class [Ljava.lang.String; --></FIELD>
		<FIELD name="_visible" type="boolean">true</FIELD>
		<FIELD name="_width" type="int">120</FIELD>
	</OBJECT>
	<OBJECT class="de.espirit.firstspirit.access.store.templatestore.FieldMapping">
		<FIELD name="_dbAttributeNames">
			<OBJECT class="java.util.HashMap">
				<OBJECT class="java.lang.String">DE</OBJECT>
				<ARRAY type="java.lang.String">
					<OBJECT class="java.lang.String">phonenumber</OBJECT>
				</ARRAY>
				<OBJECT class="java.lang.String">EN</OBJECT>
				<ARRAY type="java.lang.String">
					<OBJECT class="java.lang.String">phonenumber</OBJECT>
				</ARRAY>
			</OBJECT>
		</FIELD>
		<FIELD name="_dbReferenceName"><NULL/><!-- class java.lang.String --></FIELD>
		<FIELD name="_displayNames">
			<OBJECT class="java.util.HashMap">
				<OBJECT class="java.lang.String">DE</OBJECT>
				<OBJECT class="java.lang.String">Telefonnummer</OBJECT>
				<OBJECT class="java.lang.String">EN</OBJECT>
				<OBJECT class="java.lang.String">Phonenumber</OBJECT>
			</OBJECT>
		</FIELD>
		<FIELD name="_name">
			<OBJECT class="java.lang.String">tt_phone</OBJECT>
		</FIELD>
		<FIELD name="_valueListAttribute"><NULL/><!-- class [Ljava.lang.String; --></FIELD>
		<FIELD name="_visible" type="boolean">true</FIELD>
		<FIELD name="_width" type="int">120</FIELD>
	</OBJECT>
	<OBJECT class="de.espirit.firstspirit.access.store.templatestore.FieldMapping">
		<FIELD name="_dbAttributeNames">
			<OBJECT class="java.util.HashMap">
				<OBJECT class="java.lang.String">DE</OBJECT>
				<ARRAY type="java.lang.String">
					<OBJECT class="java.lang.String">fax</OBJECT>
				</ARRAY>
				<OBJECT class="java.lang.String">EN</OBJECT>
				<ARRAY type="java.lang.String">
					<OBJECT class="java.lang.String">fax</OBJECT>
				</ARRAY>
			</OBJECT>
		</FIELD>
		<FIELD name="_dbReferenceName"><NULL/><!-- class java.lang.String --></FIELD>
		<FIELD name="_displayNames">
			<OBJECT class="java.util.HashMap">
				<OBJECT class="java.lang.String">DE</OBJECT>
				<OBJECT class="java.lang.String">Fax</OBJECT>
				<OBJECT class="java.lang.String">EN</OBJECT>
				<OBJECT class="java.lang.String">Fax</OBJECT>
			</OBJECT>
		</FIELD>
		<FIELD name="_name">
			<OBJECT class="java.lang.String">tt_fax</OBJECT>
		</FIELD>
		<FIELD name="_valueListAttribute"><NULL/><!-- class [Ljava.lang.String; --></FIELD>
		<FIELD name="_visible" type="boolean">true</FIELD>
		<FIELD name="_width" type="int">120</FIELD>
	</OBJECT>
	<OBJECT class="de.espirit.firstspirit.access.store.templatestore.FieldMapping">
		<FIELD name="_dbAttributeNames">
			<OBJECT class="java.util.HashMap">
				<OBJECT class="java.lang.String">DE</OBJECT>
				<ARRAY type="java.lang.String">
					<OBJECT class="java.lang.String">email</OBJECT>
				</ARRAY>
				<OBJECT class="java.lang.String">EN</OBJECT>
				<ARRAY type="java.lang.String">
					<OBJECT class="java.lang.String">email</OBJECT>
				</ARRAY>
			</OBJECT>
		</FIELD>
		<FIELD name="_dbReferenceName"><NULL/><!-- class java.lang.String --></FIELD>
		<FIELD name="_displayNames">
			<OBJECT class="java.util.HashMap">
				<OBJECT class="java.lang.String">DE</OBJECT>
				<OBJECT class="java.lang.String">E-mail</OBJECT>
				<OBJECT class="java.lang.String">EN</OBJECT>
				<OBJECT class="java.lang.String">E-mail</OBJECT>
			</OBJECT>
		</FIELD>
		<FIELD name="_name">
			<OBJECT class="java.lang.String">tt_mail</OBJECT>
		</FIELD>
		<FIELD name="_valueListAttribute"><NULL/><!-- class [Ljava.lang.String; --></FIELD>
		<FIELD name="_visible" type="boolean">true</FIELD>
		<FIELD name="_width" type="int">120</FIELD>
	</OBJECT>
	<OBJECT class="de.espirit.firstspirit.access.store.templatestore.FieldMapping">
		<FIELD name="_dbAttributeNames">
			<OBJECT class="java.util.HashMap">
				<OBJECT class="java.lang.String">DE</OBJECT>
				<ARRAY type="java.lang.String">
					<OBJECT class="java.lang.String">website</OBJECT>
				</ARRAY>
				<OBJECT class="java.lang.String">EN</OBJECT>
				<ARRAY type="java.lang.String">
					<OBJECT class="java.lang.String">website</OBJECT>
				</ARRAY>
			</OBJECT>
		</FIELD>
		<FIELD name="_dbReferenceName"><NULL/><!-- class java.lang.String --></FIELD>
		<FIELD name="_displayNames">
			<OBJECT class="java.util.HashMap">
				<OBJECT class="java.lang.String">DE</OBJECT>
				<OBJECT class="java.lang.String">Website</OBJECT>
				<OBJECT class="java.lang.String">EN</OBJECT>
				<OBJECT class="java.lang.String">Website</OBJECT>
			</OBJECT>
		</FIELD>
		<FIELD name="_name">
			<OBJECT class="java.lang.String">tt_website</OBJECT>
		</FIELD>
		<FIELD name="_valueListAttribute"><NULL/><!-- class [Ljava.lang.String; --></FIELD>
		<FIELD name="_visible" type="boolean">true</FIELD>
		<FIELD name="_width" type="int">120</FIELD>
	</OBJECT>
	<OBJECT class="de.espirit.firstspirit.access.store.templatestore.FieldMapping">
		<FIELD name="_dbAttributeNames">
			<OBJECT class="java.util.HashMap">
				<OBJECT class="java.lang.String">DE</OBJECT>
				<ARRAY type="java.lang.String">
					<OBJECT class="java.lang.String">lat</OBJECT>
				</ARRAY>
				<OBJECT class="java.lang.String">EN</OBJECT>
				<ARRAY type="java.lang.String">
					<OBJECT class="java.lang.String">lat</OBJECT>
				</ARRAY>
			</OBJECT>
		</FIELD>
		<FIELD name="_dbReferenceName"><NULL/><!-- class java.lang.String --></FIELD>
		<FIELD name="_displayNames">
			<OBJECT class="java.util.HashMap">
				<OBJECT class="java.lang.String">DE</OBJECT>
				<OBJECT class="java.lang.String">Lat</OBJECT>
				<OBJECT class="java.lang.String">EN</OBJECT>
				<OBJECT class="java.lang.String">Lat</OBJECT>
			</OBJECT>
		</FIELD>
		<FIELD name="_name">
			<OBJECT class="java.lang.String">tt_lat</OBJECT>
		</FIELD>
		<FIELD name="_valueListAttribute"><NULL/><!-- class [Ljava.lang.String; --></FIELD>
		<FIELD name="_visible" type="boolean">true</FIELD>
		<FIELD name="_width" type="int">120</FIELD>
	</OBJECT>
	<OBJECT class="de.espirit.firstspirit.access.store.templatestore.FieldMapping">
		<FIELD name="_dbAttributeNames">
			<OBJECT class="java.util.HashMap">
				<OBJECT class="java.lang.String">DE</OBJECT>
				<ARRAY type="java.lang.String">
					<OBJECT class="java.lang.String">lon</OBJECT>
				</ARRAY>
				<OBJECT class="java.lang.String">EN</OBJECT>
				<ARRAY type="java.lang.String">
					<OBJECT class="java.lang.String">lon</OBJECT>
				</ARRAY>
			</OBJECT>
		</FIELD>
		<FIELD name="_dbReferenceName"><NULL/><!-- class java.lang.String --></FIELD>
		<FIELD name="_displayNames">
			<OBJECT class="java.util.HashMap">
				<OBJECT class="java.lang.String">DE</OBJECT>
				<OBJECT class="java.lang.String">Long</OBJECT>
				<OBJECT class="java.lang.String">EN</OBJECT>
				<OBJECT class="java.lang.String">Long</OBJECT>
			</OBJECT>
		</FIELD>
		<FIELD name="_name">
			<OBJECT class="java.lang.String">tt_long</OBJECT>
		</FIELD>
		<FIELD name="_valueListAttribute"><NULL/><!-- class [Ljava.lang.String; --></FIELD>
		<FIELD name="_visible" type="boolean">true</FIELD>
		<FIELD name="_width" type="int">120</FIELD>
	</OBJECT>
	<OBJECT class="de.espirit.firstspirit.access.store.templatestore.FieldMapping">
		<FIELD name="_dbAttributeNames">
			<OBJECT class="java.util.HashMap">
				<OBJECT class="java.lang.String">DE</OBJECT>
				<ARRAY type="java.lang.String">
					<OBJECT class="java.lang.String">country</OBJECT>
				</ARRAY>
				<OBJECT class="java.lang.String">EN</OBJECT>
				<ARRAY type="java.lang.String">
					<OBJECT class="java.lang.String">country</OBJECT>
				</ARRAY>
			</OBJECT>
		</FIELD>
		<FIELD name="_dbReferenceName"><NULL/><!-- class java.lang.String --></FIELD>
		<FIELD name="_displayNames">
			<OBJECT class="java.util.HashMap">
				<OBJECT class="java.lang.String">DE</OBJECT>
				<OBJECT class="java.lang.String">Land</OBJECT>
				<OBJECT class="java.lang.String">EN</OBJECT>
				<OBJECT class="java.lang.String">Country</OBJECT>
			</OBJECT>
		</FIELD>
		<FIELD name="_name">
			<OBJECT class="java.lang.String">lt_country</OBJECT>
		</FIELD>
		<FIELD name="_valueListAttribute"><NULL/><!-- class [Ljava.lang.String; --></FIELD>
		<FIELD name="_visible" type="boolean">true</FIELD>
		<FIELD name="_width" type="int">120</FIELD>
	</OBJECT>
	<OBJECT class="de.espirit.firstspirit.access.store.templatestore.FieldMapping">
		<FIELD name="_dbAttributeNames">
			<OBJECT class="java.util.HashMap">
				<OBJECT class="java.lang.String">DE</OBJECT>
				<ARRAY type="java.lang.String">
					<OBJECT class="java.lang.String">priority</OBJECT>
				</ARRAY>
				<OBJECT class="java.lang.String">EN</OBJECT>
				<ARRAY type="java.lang.String">
					<OBJECT class="java.lang.String">priority</OBJECT>
				</ARRAY>
			</OBJECT>
		</FIELD>
		<FIELD name="_dbReferenceName"><NULL/><!-- class java.lang.String --></FIELD>
		<FIELD name="_displayNames">
			<OBJECT class="java.util.HashMap">
				<OBJECT class="java.lang.String">DE</OBJECT>
				<OBJECT class="java.lang.String">Priorität</OBJECT>
				<OBJECT class="java.lang.String">EN</OBJECT>
				<OBJECT class="java.lang.String">Priorität</OBJECT>
			</OBJECT>
		</FIELD>
		<FIELD name="_name">
			<OBJECT class="java.lang.String">tt_priority</OBJECT>
		</FIELD>
		<FIELD name="_valueListAttribute"><NULL/><!-- class [Ljava.lang.String; --></FIELD>
		<FIELD name="_visible" type="boolean">true</FIELD>
		<FIELD name="_width" type="int">120</FIELD>
	</OBJECT>
</ARRAY>
